pynet/__init__.py
gluon_qemu_testlab-0.0.5.dist-info/LICENSE
gluon_qemu_testlab-0.0.5.dist-info/METADATA
gluon_qemu_testlab-0.0.5.dist-info/WHEEL
gluon_qemu_testlab-0.0.5.dist-info/top_level.txt
gluon_qemu_testlab-0.0.5.dist-info/RECORD
