Metadata-Version: 2.1
Name: gluon-qemu-testlab
Version: 0.0.5
Summary: Python scripts to run qemu and gluon based virtual mesh networks
Home-page: https://github.com/freifunk-gluon/gluon-qemu-testlab
Author: Leonardo Mörlein
Author-email: me@irrelefant.net
License: UNKNOWN
Platform: UNKNOWN
Classifier: Programming Language :: Python :: 3
Classifier: License :: OSI Approved :: MIT License
Classifier: Operating System :: OS Independent
Requires-Python: >=3.6
Requires-Dist: asyncssh (==2.1.0)
